{
  "Army1Name": "444",
  "Army1Prefix": null,
  "Army1Color": 12,
  "Army1Units": [
    {
      "Type": "StrongFighter",
      "FighterNumber": 1,
      "Health": -3,
      "Attack": 20,
      "Defence": 15,
      "Cost": 40
    },
    {
      "Type": "ShieldWall",
      "FighterNumber": 2,
      "Health": 41,
      "Attack": 0,
      "Defence": 50,
      "Cost": 55
    },
    {
      "Type": "WeakFighter",
      "FighterNumber": 3,
      "Health": -3,
      "Attack": 10,
      "Defence": 8,
      "Cost": 15
    },
    {
      "Type": "Healer",
      "FighterNumber": 4,
      "Health": -5,
      "Attack": 3,
      "Defence": 2,
      "Cost": 20
    },
    {
      "Type": "StrongFighter",
      "FighterNumber": 5,
      "Health": 0,
      "Attack": 20,
      "Defence": 15,
      "Cost": 40
    },
    {
      "Type": "Wizard",
      "FighterNumber": 6,
      "Health": -2,
      "Attack": 7,
      "Defence": 4,
      "Cost": 30
    }
  ],
  "TotalCost1": 200,
  "Army2Name": "555",
  "Army2Prefix": null,
  "Army2Color": 9,
  "Army2Units": [
    {
      "Type": "StrongFighter",
      "FighterNumber": 1,
      "Health": 20,
      "Attack": 20,
      "Defence": 15,
      "Cost": 40
    },
    {
      "Type": "Archer",
      "FighterNumber": 2,
      "Health": 18,
      "Attack": 5,
      "Defence": 3,
      "Cost": 25
    },
    {
      "Type": "WeakFighter",
      "FighterNumber": 3,
      "Health": 25,
      "Attack": 10,
      "Defence": 8,
      "Cost": 15
    },
    {
      "Type": "StrongFighter",
      "FighterNumber": 4,
      "Health": 0,
      "Attack": 20,
      "Defence": 15,
      "Cost": 40
    },
    {
      "Type": "Healer",
      "FighterNumber": 5,
      "Health": -3,
      "Attack": 3,
      "Defence": 2,
      "Cost": 20
    },
    {
      "Type": "ShieldWall",
      "FighterNumber": 6,
      "Health": 70,
      "Attack": 0,
      "Defence": 50,
      "Cost": 55
    }
  ],
  "TotalCost2": 195,
  "SaveDate": "2026-04-02T12:35:30.8505795+03:00",
  "CurrentRound": 1,
  "AttackTurn": 0,
  "Army1CurrentFighterIndex": 1,
  "Army2CurrentFighterIndex": 1,
  "FirstAttackerIsArmy1": false,
  "NeedNewRoundHeader": true,
  "Army1AliveOrder": [
    2
  ],
  "Army2AliveOrder": [
    1,
    3,
    6,
    2
  ],
  "BattleLogName": null
}