{
  "Army1Name": "\u0434\u0430",
  "Army1Prefix": null,
  "Army1Color": 12,
  "Army1Units": [
    {
      "Type": "Healer",
      "FighterNumber": 1,
      "Health": -5,
      "Attack": 3,
      "Defence": 2,
      "Cost": 20
    },
    {
      "Type": "ShieldWall",
      "FighterNumber": 2,
      "Health": 23,
      "Attack": 0,
      "Defence": 50,
      "Cost": 55
    },
    {
      "Type": "Archer",
      "FighterNumber": 3,
      "Health": -7,
      "Attack": 5,
      "Defence": 3,
      "Cost": 25
    },
    {
      "Type": "ShieldWall",
      "FighterNumber": 4,
      "Health": 65,
      "Attack": 0,
      "Defence": 50,
      "Cost": 55
    },
    {
      "Type": "StrongFighter",
      "FighterNumber": 5,
      "Health": 60,
      "Attack": 20,
      "Defence": 15,
      "Cost": 40
    },
    {
      "Type": "ShieldWall",
      "FighterNumber": 6,
      "Health": 70,
      "Attack": 0,
      "Defence": 50,
      "Cost": 55
    },
    {
      "Type": "WeakFighter",
      "FighterNumber": 7,
      "Health": -1,
      "Attack": 10,
      "Defence": 8,
      "Cost": 15
    },
    {
      "Type": "StrongFighter",
      "FighterNumber": 8,
      "Health": 59,
      "Attack": 20,
      "Defence": 15,
      "Cost": 40
    },
    {
      "Type": "ShieldWall",
      "FighterNumber": 9,
      "Health": 70,
      "Attack": 0,
      "Defence": 50,
      "Cost": 55
    },
    {
      "Type": "Wizard",
      "FighterNumber": 10,
      "Health": 6,
      "Attack": 7,
      "Defence": 4,
      "Cost": 30
    }
  ],
  "TotalCost1": 390,
  "Army2Name": "\u0436\u0430",
  "Army2Prefix": null,
  "Army2Color": 9,
  "Army2Units": [
    {
      "Type": "WeakFighter",
      "FighterNumber": 22,
      "Health": 25,
      "Attack": 10,
      "Defence": 8,
      "Cost": 15
    },
    {
      "Type": "WeakFighter",
      "FighterNumber": 25,
      "Health": 25,
      "Attack": 10,
      "Defence": 8,
      "Cost": 15
    },
    {
      "Type": "Archer",
      "FighterNumber": 20,
      "Health": 18,
      "Attack": 5,
      "Defence": 3,
      "Cost": 25
    },
    {
      "Type": "WeakFighter",
      "FighterNumber": 21,
      "Health": 25,
      "Attack": 10,
      "Defence": 8,
      "Cost": 15
    },
    {
      "Type": "WeakFighter",
      "FighterNumber": 18,
      "Health": 25,
      "Attack": 10,
      "Defence": 8,
      "Cost": 15
    },
    {
      "Type": "Archer",
      "FighterNumber": 23,
      "Health": 18,
      "Attack": 5,
      "Defence": 3,
      "Cost": 25
    },
    {
      "Type": "WeakFighter",
      "FighterNumber": 17,
      "Health": 25,
      "Attack": 10,
      "Defence": 8,
      "Cost": 15
    },
    {
      "Type": "WeakFighter",
      "FighterNumber": 1,
      "Health": 25,
      "Attack": 10,
      "Defence": 8,
      "Cost": 15
    },
    {
      "Type": "Wizard",
      "FighterNumber": 2,
      "Health": 22,
      "Attack": 7,
      "Defence": 4,
      "Cost": 30
    },
    {
      "Type": "WeakFighter",
      "FighterNumber": 3,
      "Health": 25,
      "Attack": 10,
      "Defence": 8,
      "Cost": 15
    },
    {
      "Type": "Archer",
      "FighterNumber": 24,
      "Health": 18,
      "Attack": 5,
      "Defence": 3,
      "Cost": 25
    },
    {
      "Type": "Wizard",
      "FighterNumber": 4,
      "Health": 22,
      "Attack": 7,
      "Defence": 4,
      "Cost": 30
    },
    {
      "Type": "Wizard",
      "FighterNumber": 5,
      "Health": 22,
      "Attack": 7,
      "Defence": 4,
      "Cost": 30
    },
    {
      "Type": "Archer",
      "FighterNumber": 6,
      "Health": 18,
      "Attack": 5,
      "Defence": 3,
      "Cost": 25
    },
    {
      "Type": "Wizard",
      "FighterNumber": 7,
      "Health": 22,
      "Attack": 7,
      "Defence": 4,
      "Cost": 30
    },
    {
      "Type": "Archer",
      "FighterNumber": 19,
      "Health": 18,
      "Attack": 5,
      "Defence": 3,
      "Cost": 25
    },
    {
      "Type": "Healer",
      "FighterNumber": 8,
      "Health": 15,
      "Attack": 3,
      "Defence": 2,
      "Cost": 20
    },
    {
      "Type": "Healer",
      "FighterNumber": 9,
      "Health": 15,
      "Attack": 3,
      "Defence": 2,
      "Cost": 20
    },
    {
      "Type": "WeakFighter",
      "FighterNumber": 10,
      "Health": 25,
      "Attack": 10,
      "Defence": 8,
      "Cost": 15
    },
    {
      "Type": "Wizard",
      "FighterNumber": 11,
      "Health": 22,
      "Attack": 7,
      "Defence": 4,
      "Cost": 30
    },
    {
      "Type": "ShieldWall",
      "FighterNumber": 12,
      "Health": 70,
      "Attack": 0,
      "Defence": 50,
      "Cost": 55
    },
    {
      "Type": "WeakFighter",
      "FighterNumber": 13,
      "Health": 25,
      "Attack": 10,
      "Defence": 8,
      "Cost": 15
    },
    {
      "Type": "Archer",
      "FighterNumber": 14,
      "Health": 18,
      "Attack": 5,
      "Defence": 3,
      "Cost": 25
    },
    {
      "Type": "Archer",
      "FighterNumber": 15,
      "Health": 18,
      "Attack": 5,
      "Defence": 3,
      "Cost": 25
    },
    {
      "Type": "Healer",
      "FighterNumber": 16,
      "Health": 15,
      "Attack": 3,
      "Defence": 2,
      "Cost": 20
    }
  ],
  "TotalCost2": 575,
  "SaveDate": "2026-04-20T15:26:32.5579744+03:00",
  "CurrentRound": 1,
  "AttackTurn": 0,
  "Army1CurrentFighterIndex": 0,
  "Army2CurrentFighterIndex": 0,
  "FirstAttackerIsArmy1": false,
  "NeedNewRoundHeader": true,
  "Army1AliveOrder": [],
  "Army2AliveOrder": [],
  "BattleLogName": null,
  "MoveCount": 0
}