{
  "Army1Name": "eudkjc",
  "Army1Prefix": null,
  "Army1Color": 12,
  "Army1Units": [
    {
      "Type": "Healer",
      "FighterNumber": 1,
      "Health": 15,
      "Attack": 3,
      "Defence": 2,
      "Cost": 20
    },
    {
      "Type": "Healer",
      "FighterNumber": 2,
      "Health": 15,
      "Attack": 3,
      "Defence": 2,
      "Cost": 20
    },
    {
      "Type": "ShieldWall",
      "FighterNumber": 3,
      "Health": 70,
      "Attack": 0,
      "Defence": 50,
      "Cost": 55
    },
    {
      "Type": "ShieldWall",
      "FighterNumber": 4,
      "Health": 70,
      "Attack": 0,
      "Defence": 50,
      "Cost": 55
    },
    {
      "Type": "StrongFighter",
      "FighterNumber": 5,
      "Health": 60,
      "Attack": 20,
      "Defence": 15,
      "Cost": 40
    },
    {
      "Type": "WeakFighter",
      "FighterNumber": 6,
      "Health": 25,
      "Attack": 10,
      "Defence": 8,
      "Cost": 15
    },
    {
      "Type": "Archer",
      "FighterNumber": 7,
      "Health": 18,
      "Attack": 5,
      "Defence": 3,
      "Cost": 25
    },
    {
      "Type": "Healer",
      "FighterNumber": 8,
      "Health": 15,
      "Attack": 3,
      "Defence": 2,
      "Cost": 20
    },
    {
      "Type": "WeakFighter",
      "FighterNumber": 9,
      "Health": 25,
      "Attack": 10,
      "Defence": 8,
      "Cost": 15
    },
    {
      "Type": "Archer",
      "FighterNumber": 10,
      "Health": 18,
      "Attack": 5,
      "Defence": 3,
      "Cost": 25
    }
  ],
  "TotalCost1": 290,
  "Army2Name": "xc,jdsk",
  "Army2Prefix": null,
  "Army2Color": 9,
  "Army2Units": [
    {
      "Type": "ShieldWall",
      "FighterNumber": 1,
      "Health": 70,
      "Attack": 0,
      "Defence": 50,
      "Cost": 55
    },
    {
      "Type": "StrongFighter",
      "FighterNumber": 2,
      "Health": 60,
      "Attack": 20,
      "Defence": 15,
      "Cost": 40
    },
    {
      "Type": "Healer",
      "FighterNumber": 3,
      "Health": 15,
      "Attack": 3,
      "Defence": 2,
      "Cost": 20
    },
    {
      "Type": "Healer",
      "FighterNumber": 4,
      "Health": 15,
      "Attack": 3,
      "Defence": 2,
      "Cost": 20
    },
    {
      "Type": "ShieldWall",
      "FighterNumber": 5,
      "Health": 70,
      "Attack": 0,
      "Defence": 50,
      "Cost": 55
    },
    {
      "Type": "Wizard",
      "FighterNumber": 6,
      "Health": 22,
      "Attack": 7,
      "Defence": 4,
      "Cost": 30
    },
    {
      "Type": "Archer",
      "FighterNumber": 7,
      "Health": 18,
      "Attack": 5,
      "Defence": 3,
      "Cost": 25
    },
    {
      "Type": "Healer",
      "FighterNumber": 8,
      "Health": 15,
      "Attack": 3,
      "Defence": 2,
      "Cost": 20
    },
    {
      "Type": "WeakFighter",
      "FighterNumber": 9,
      "Health": 25,
      "Attack": 10,
      "Defence": 8,
      "Cost": 15
    },
    {
      "Type": "WeakFighter",
      "FighterNumber": 10,
      "Health": 25,
      "Attack": 10,
      "Defence": 8,
      "Cost": 15
    }
  ],
  "TotalCost2": 295,
  "SaveDate": "2026-04-23T10:45:56.4975431+03:00",
  "CurrentRound": 0,
  "AttackTurn": 0,
  "Army1CurrentFighterIndex": 0,
  "Army2CurrentFighterIndex": 0,
  "FirstAttackerIsArmy1": false,
  "NeedNewRoundHeader": true,
  "Army1AliveOrder": [
    6,
    9,
    1,
    2,
    3,
    4,
    5,
    7,
    8,
    10
  ],
  "Army2AliveOrder": [
    9,
    10,
    1,
    2,
    3,
    4,
    5,
    6,
    7,
    8
  ],
  "BattleLogName": "eudkjc vs xc,jdsk",
  "MoveCount": 0,
  "CurrentFormation": 2
}